keyra/__init__.py
keyra/key.py
keyra-1.0.0.dist-info/licenses/LICENSE
keyra-1.0.0.dist-info/METADATA
keyra-1.0.0.dist-info/WHEEL
keyra-1.0.0.dist-info/top_level.txt
keyra-1.0.0.dist-info/RECORD
