Metadata-Version: 2.4
Name: keyra
Version: 1.0.0
Summary: Tool for quick necessary stuff
Author: jisan
Author-email: realterm.io@gmail.com
Classifier: Programming Language :: Python :: 3
Classifier: License :: OSI Approved :: MIT License
Classifier: Operating System :: OS Independent
Requires-Python: >=3.5
License-File: LICENSE
Dynamic: license-file
